lyj.py
xiaolanjing-1.0.dist-info/METADATA
xiaolanjing-1.0.dist-info/WHEEL
xiaolanjing-1.0.dist-info/top_level.txt
xiaolanjing-1.0.dist-info/RECORD
