Metadata-Version: 2.1
Name: xiaolanjing
Version: 1.0
Summary: 大数据3
Home-page: UNKNOWN
Author: 京京
Author-email: 1752844391@qq.com
License: UNKNOWN
Platform: UNKNOWN
